arxiv_search_mcp_server/__init__.py
arxiv_search_mcp_server/__main__.py
arxiv_search_mcp_server/server.py
arxiv_search_mcp_server-0.1.2.dist-info/licenses/LICENSE
arxiv_search_mcp_server-0.1.2.dist-info/METADATA
arxiv_search_mcp_server-0.1.2.dist-info/WHEEL
arxiv_search_mcp_server-0.1.2.dist-info/entry_points.txt
arxiv_search_mcp_server-0.1.2.dist-info/top_level.txt
arxiv_search_mcp_server-0.1.2.dist-info/RECORD
