Metadata-Version: 2.4
Name: arxiv-search-mcp-server
Version: 0.1.2
Summary: An MCP server that provides search functionality for arXiv.org papers
Home-page: https://github.com/gavinHuang/arxiv-search-mcp
Author: Gavin Huang
Author-email: Gavin Huang <gavin@example.com>
Maintainer-email: Gavin Huang <gavin@example.com>
License-Expression: MIT
Project-URL: Homepage, https://github.com/gavinHuang/arxiv-search-mcp
Project-URL: Documentation, https://github.com/gavinHuang/arxiv-search-mcp/blob/main/README.md
Project-URL: Repository, https://github.com/gavinHuang/arxiv-search-mcp
Project-URL: Bug Tracker, https://github.com/gavinHuang/arxiv-search-mcp/issues
Keywords: arxiv,mcp,search,papers,research,model-context-protocol
Classifier: Development Status :: 3 - Alpha
Classifier: Intended Audience :: Developers
Classifier: Intended Audience :: Science/Research
Classifier: Operating System :: OS Independent
Classifier: Programming Language :: Python :: 3
Classifier: Programming Language :: Python :: 3.8
Classifier: Programming Language :: Python :: 3.9
Classifier: Programming Language :: Python :: 3.10
Classifier: Programming Language :: Python :: 3.11
Classifier: Programming Language :: Python :: 3.12
Classifier: Topic :: Scientific/Engineering
Classifier: Topic :: Software Development :: Libraries :: Python Modules
Classifier: Topic :: Internet :: WWW/HTTP :: Indexing/Search
Requires-Python: >=3.8
License-File: LICENSE
Requires-Dist: fastmcp
Requires-Dist: requests
Requires-Dist: feedparser
Requires-Dist: urllib3
Provides-Extra: dev
Requires-Dist: pytest>=6.0; extra == "dev"
Requires-Dist: pytest-asyncio; extra == "dev"
Requires-Dist: black; extra == "dev"
Requires-Dist: flake8; extra == "dev"
Requires-Dist: mypy; extra == "dev"
Dynamic: author
Dynamic: home-page
Dynamic: license-file
Dynamic: requires-python
